vsthost.cpython-313-darwin.so
insthost-0.3.0.dist-info/METADATA
insthost-0.3.0.dist-info/WHEEL
insthost-0.3.0.dist-info/top_level.txt
insthost-0.3.0.dist-info/RECORD
