Metadata-Version: 2.4
Name: insthost
Version: 0.3.0
Summary: Python bindings for c++ VST Instrument Host!
Author: sinesurge
Dynamic: author
Dynamic: summary
